flask_tus
