Metadata-Version: 1.1
Name: Flask-Tus
Version: 0.3.0
Summary: TUS protocol implementation
Home-page: http://github.com/matthoskins1980/Flask-Tus/
Author: Matt Hoskins
Author-email: matt.hoski+flask-tus@gmail.com
License: MIT
Platform: any
Classifier: Environment :: Web Environment
Classifier: Intended Audience :: Developers
Classifier: License :: OSI Approved :: MIT License
Classifier: Operating System :: OS Independent
Classifier: Programming Language :: Python
Classifier: Topic :: Software Development :: Libraries :: Python Modules
